pyenvcfg/__init__.py
pyenvcfg/pyenvcfg.py
pyenvcfg/utils/utils.py
pyenvcfg/version.py
pyenvcfg-0.1.5.dist-info/LICENSE
pyenvcfg-0.1.5.dist-info/METADATA
pyenvcfg-0.1.5.dist-info/WHEEL
pyenvcfg-0.1.5.dist-info/entry_points.txt
pyenvcfg-0.1.5.dist-info/RECORD
