Metadata-Version: 2.1
Name: pyenvcfg
Version: 0.1.5
Summary: 
Author: Juan Carlos Gutierrez
Author-email: jgutierrez@contractor.ea.com
Requires-Python: >=3.10,<4.0
Classifier: Programming Language :: Python :: 3
Classifier: Programming Language :: Python :: 3.10
Classifier: Programming Language :: Python :: 3.11
Classifier: Programming Language :: Python :: 3.12
Requires-Dist: click (>=8.1.7,<9.0.0)
Requires-Dist: gitpython (>=3.1.43,<4.0.0)
Requires-Dist: jcgutier-logger (>=0.1.1,<0.2.0)
Requires-Dist: toml (>=0.10.2,<0.11.0)
